multion/__init__.py
multion/base_client.py
multion/client.py
multion/core/__init__.py
multion/core/api_error.py
multion/core/client_wrapper.py
multion/core/datetime_utils.py
multion/core/file.py
multion/core/http_client.py
multion/core/jsonable_encoder.py
multion/core/pydantic_utilities.py
multion/core/query_encoder.py
multion/core/remove_none_from_dict.py
multion/core/request_options.py
multion/core/unchecked_base_model.py
multion/environment.py
multion/errors/__init__.py
multion/errors/bad_request_error.py
multion/errors/internal_server_error.py
multion/errors/payment_required_error.py
multion/errors/unauthorized_error.py
multion/errors/unprocessable_entity_error.py
multion/py.typed
multion/sessions/__init__.py
multion/sessions/client.py
multion/sessions/types/__init__.py
multion/sessions/types/create_session_input_browser_params.py
multion/sessions/types/sessions_close_response.py
multion/sessions/types/sessions_list_response.py
multion/sessions/types/sessions_screenshot_response.py
multion/sessions/types/sessions_step_request_browser_params.py
multion/sessions/types/sessions_step_stream_request_browser_params.py
multion/sessions/wrapped_client.py
multion/types/__init__.py
multion/types/bad_request_response.py
multion/types/browse_output.py
multion/types/format.py
multion/types/http_validation_error.py
multion/types/internal_server_error_response.py
multion/types/metadata.py
multion/types/mode.py
multion/types/payment_required_response.py
multion/types/remote_value.py
multion/types/retrieve_output.py
multion/types/session_created.py
multion/types/session_step_stream_chunk.py
multion/types/session_step_success.py
multion/types/session_step_success_metadata.py
multion/types/session_stream_chunk_event.py
multion/types/session_stream_chunk_event_data.py
multion/types/session_stream_chunk_event_data_delta.py
multion/types/session_stream_chunk_final_event.py
multion/types/session_stream_chunk_final_event_data.py
multion-1.3.8.dist-info/METADATA
multion-1.3.8.dist-info/WHEEL
multion-1.3.8.dist-info/RECORD
